inferaapi/__init__.py
inferaapi/app.py
inferaapi/config.py
inferaapi/exceptions.py
inferaapi/utils.py
inferaapi/models/__init__.py
inferaapi/models/base.py
inferaapi/models/providers/__init__.py
inferaapi/models/providers/anthropic.py
inferaapi/models/providers/custom.py
inferaapi/models/providers/huggingface.py
inferaapi/models/providers/openai.py
inferaapi/routes/__init__.py
inferaapi/routes/api.py
inferaapi/routes/docs.py
inferaapi/schemas/__init__.py
inferaapi/schemas/requests.py
inferaapi/schemas/responses.py
inferaapi-0.1.0.dist-info/licenses/LICENSE
inferaapi-0.1.0.dist-info/METADATA
inferaapi-0.1.0.dist-info/WHEEL
inferaapi-0.1.0.dist-info/entry_points.txt
inferaapi-0.1.0.dist-info/top_level.txt
inferaapi-0.1.0.dist-info/RECORD
