Metadata-Version: 2.4
Name: inferaapi
Version: 0.1.0
Summary: An open-source Python REST API framework with built-in Generative AI integration.
Home-page: https://github.com/inferaapi/inferaapi
Author: Pankaj Kumar
Author-email: Pankaj Kumar <inferaapi@gmail.com>
License: ```text
Project-URL: Homepage, https://github.com/inferaapi/inferaapi
Project-URL: Documentation, https://github.com/inferaapi/inferaapi#readme
Project-URL: Repository, https://github.com/inferaapi/inferaapi
Project-URL: Issues, https://github.com/inferaapi/inferaapi/issues
Project-URL: Changelog, https://github.com/inferaapi/inferaapi/releases
Classifier: Development Status :: 3 - Alpha
Classifier: Intended Audience :: Developers
Classifier: Intended Audience :: Science/Research
Classifier: Programming Language :: Python :: 3
Classifier: Programming Language :: Python :: 3.10
Classifier: Programming Language :: Python :: 3.11
Classifier: Programming Language :: Python :: 3.12
Classifier: Topic :: Software Development :: Libraries :: Application Frameworks
Classifier: Topic :: Scientific/Engineering :: Artificial Intelligence
Classifier: License :: OSI Approved :: MIT License
Requires-Python: >=3.10
License-File: LICENSE
Requires-Dist: starlette>=0.27.0
Requires-Dist: uvicorn[standard]>=0.23.0
Requires-Dist: pydantic>=2.0.0
Requires-Dist: pydantic-settings>=2.0.0
Requires-Dist: openai>=1.0.0
Requires-Dist: anthropic>=0.7.0
Requires-Dist: transformers>=4.34.0
Requires-Dist: torch>=2.0.0
Requires-Dist: numpy<2.0.0,>=1.21.0
Requires-Dist: requests>=2.31.0
Requires-Dist: python-multipart>=0.0.6
Requires-Dist: python-jose>=3.3.0
Requires-Dist: passlib>=1.7.4
Requires-Dist: aiofiles>=23.2.0
Requires-Dist: python-dotenv>=1.0.0
Requires-Dist: httpx>=0.25.0
Provides-Extra: dev
Requires-Dist: pytest>=7.0.0; extra == "dev"
Requires-Dist: pytest-asyncio>=0.21.0; extra == "dev"
Requires-Dist: pytest-cov>=4.0.0; extra == "dev"
Requires-Dist: pytest-httpx>=0.27.0; extra == "dev"
Requires-Dist: flake8>=6.0.0; extra == "dev"
Requires-Dist: black>=23.0.0; extra == "dev"
Requires-Dist: isort>=5.12.0; extra == "dev"
Requires-Dist: mypy>=1.0.0; extra == "dev"
Requires-Dist: build>=0.10.0; extra == "dev"
Requires-Dist: twine>=4.0.0; extra == "dev"
Requires-Dist: httpx>=0.25.0; extra == "dev"
Dynamic: author
Dynamic: home-page
Dynamic: license-file
Dynamic: requires-python
